pluto_rt/.DS_Store
pluto_rt/__init__.py
pluto_rt/apps.py
pluto_rt/urls.py
pluto_rt/views.py
pluto_rt/templates/.DS_Store
pluto_rt/templates/pluto_rt/rows.html
pluto_rt/templates/pluto_rt/table.html
pluto_rt-0.1.1.dist-info/METADATA
pluto_rt-0.1.1.dist-info/WHEEL
pluto_rt-0.1.1.dist-info/licenses/LICENSE
pluto_rt-0.1.1.dist-info/RECORD
