Metadata-Version: 2.1
Name: pluto_rt
Version: 0.1.1
Summary: A reusable Django app providing a kit for storing and displaying messages from a background processor into a web view in real time, as the processor works.
Project-URL: Homepage, https://github.com/shacker/pluto
Author-email: Scot Hacker <shacker@birdhouse.org>
License-File: LICENSE
Classifier: License :: OSI Approved :: MIT License
Classifier: Operating System :: OS Independent
Classifier: Programming Language :: Python :: 3
Requires-Python: >=3.10
Requires-Dist: qr3
